Slb.Salmon.Zgy.dll
zfp.dll
zgy2sgz.cp36-win_amd64.pyd
zgy2sgz.dll
zgy2sgz-0.1.3.dist-info/LICENSE
zgy2sgz-0.1.3.dist-info/METADATA
zgy2sgz-0.1.3.dist-info/WHEEL
zgy2sgz-0.1.3.dist-info/top_level.txt
zgy2sgz-0.1.3.dist-info/RECORD
