Metadata-Version: 2.1
Name: zgy2sgz
Version: 0.1.3
Summary: Convert zgy files to sgz files
Home-page: https://github.com/equinor/zgy2sgz
Author: Equinor
License: Apache License 2.0
Platform: UNKNOWN
License-File: LICENSE
